canmatrix/__init__.py
canmatrix/cancluster.py
canmatrix/canmatrix.py
canmatrix/compare.py
canmatrix/convert.py
canmatrix/copy.py
canmatrix/j1939.dbc
canmatrix/j1939_decoder.py
canmatrix/join.py
canmatrix/log.py
canmatrix/py.typed
canmatrix/types.py
canmatrix/utils.py
canmatrix/cli/__init__.py
canmatrix/cli/compare.py
canmatrix/cli/convert.py
canmatrix/formats/__init__.py
canmatrix/formats/arxml.py
canmatrix/formats/csv.py
canmatrix/formats/dbc.py
canmatrix/formats/dbf.py
canmatrix/formats/eds.py
canmatrix/formats/fibex.py
canmatrix/formats/json.py
canmatrix/formats/kcd.py
canmatrix/formats/ldf.py
canmatrix/formats/odx.py
canmatrix/formats/scapy.py
canmatrix/formats/sym.py
canmatrix/formats/wireshark.py
canmatrix/formats/xls.py
canmatrix/formats/xls_common.py
canmatrix/formats/xlsx.py
canmatrix/formats/yaml.py
testpypi_canmatrix-1.2.0.dist-info/licenses/LICENSE
testpypi_canmatrix-1.2.0.dist-info/METADATA
testpypi_canmatrix-1.2.0.dist-info/WHEEL
testpypi_canmatrix-1.2.0.dist-info/entry_points.txt
testpypi_canmatrix-1.2.0.dist-info/top_level.txt
testpypi_canmatrix-1.2.0.dist-info/RECORD
