Metadata-Version: 2.4
Name: testpypi-canmatrix
Version: 1.2.0
Summary: Automotive Communication Matrix
Author-email: Eduard Bröcker <eduard@gmx.de>
Maintainer: canmatrix contributors
License: BSD-2-Clause
Project-URL: homepage, https://github.com/ebroecker/canmatrix
Project-URL: documentation, https://canmatrix.readthedocs.io
Project-URL: repository, https://github.com/ebroecker/canmatrix
Keywords: CAN,canbus,dbc,arxml,kcd,dbf,sym,fibex,eds,automotive
Classifier: Development Status :: 5 - Production/Stable
Classifier: Environment :: Console
Classifier: Intended Audience :: Developers
Classifier: Intended Audience :: Education
Classifier: Intended Audience :: Information Technology
Classifier: Intended Audience :: Manufacturing
Classifier: Intended Audience :: Telecommunications Industry
Classifier: License :: OSI Approved :: BSD License
Classifier: Operating System :: Microsoft :: Windows
Classifier: Operating System :: POSIX :: Linux
Classifier: Operating System :: MacOS
Classifier: Programming Language :: Python
Classifier: Programming Language :: Python :: 3.8
Classifier: Programming Language :: Python :: 3.9
Classifier: Programming Language :: Python :: 3.10
Classifier: Programming Language :: Python :: 3.11
Classifier: Programming Language :: Python :: 3.12
Classifier: Programming Language :: Python :: 3.13
Classifier: Topic :: Software Development :: Embedded Systems :: Controller Area Network (CAN)
Classifier: Topic :: System :: Networking
Classifier: Topic :: Utilities
Requires-Python: >=3.8
License-File: LICENSE
Requires-Dist: attrs>=19.2.0
Requires-Dist: click
Requires-Dist: importlib-metadata; python_version < "3.8"
Requires-Dist: typing; python_version < "3.5"
Provides-Extra: arxml
Requires-Dist: lxml; extra == "arxml"
Provides-Extra: csv
Provides-Extra: dbc
Provides-Extra: dbf
Provides-Extra: fibex
Requires-Dist: lxml; extra == "fibex"
Provides-Extra: json
Provides-Extra: kcd
Requires-Dist: lxml; extra == "kcd"
Provides-Extra: ldf
Requires-Dist: ldfparser; extra == "ldf"
Provides-Extra: odx
Requires-Dist: lxml; extra == "odx"
Provides-Extra: scapy
Provides-Extra: sym
Provides-Extra: test
Requires-Dist: pathlib2; python_version < "3.4" and extra == "test"
Requires-Dist: pytest; extra == "test"
Provides-Extra: wireshark
Provides-Extra: xls
Requires-Dist: xlrd==1.2.0; extra == "xls"
Requires-Dist: xlwt; extra == "xls"
Provides-Extra: xlsx
Requires-Dist: openpyxl; extra == "xlsx"
Provides-Extra: yaml
Requires-Dist: pyyaml; extra == "yaml"
Provides-Extra: eds
Requires-Dist: canopen; extra == "eds"
Dynamic: license-file
